<?xml version="1.0" encoding="UTF-8"?>
<AdminMessage version="1.0" xmlns="http://www.surescripts.com/directories">	<Header>		<To>mailto:sssdir.tp@surescripts.com</To>		<From>mailto:glenwd.tp@surescripts.com</From>		<MessageID>228017336</MessageID>		<SentTime>2008-03-30T05:44:06.0Z</SentTime>		<Authentication>			<LoginID>smanickaraj</LoginID>			<Password>man5550!</Password>		</Authentication>	</Header>	<Body>		<DirectoryDownloadNightlyPharmacyURL>			<PartnerAccountID>243</PartnerAccountID>			<ReportDate>2008-03-30</ReportDate>			<VersionID>3</VersionID>		</DirectoryDownloadNightlyPharmacyURL>	</Body></AdminMessage>